AUTHORS
ChangeLog
Readme.rst
requirements.txt
setup.cfg
setup.py
teleirc/__init__.py
teleirc.egg-info/PKG-INFO
teleirc.egg-info/SOURCES.txt
teleirc.egg-info/dependency_links.txt
teleirc.egg-info/entry_points.txt
teleirc.egg-info/not-zip-safe
teleirc.egg-info/pbr.json
teleirc.egg-info/requires.txt
teleirc.egg-info/top_level.txt