Metadata-Version: 1.1
Name: teleirc
Version: 0.0.0
Summary: Telegram IRC
Home-page: https://github.com/XayOn/teleirc
Author: David Francos Cuartero
Author-email: opensource@davidfrancos.net
License: Apache-2
Platform: UNKNOWN
Classifier: Development Status :: 5 - Production/Stable
Classifier: Environment :: Console
Classifier: Intended Audience :: End Users/Desktop
Classifier: License :: OSI Approved :: GNU General Public License (GPL)
Classifier: Operating System :: OS Independent
Classifier: Programming Language :: Python :: 3.5
Classifier: Programming Language :: Python :: 3 :: Only
